<?xml version="1.0" encoding="utf-8" ?>
<elements>
	<info>
		<update version="0.1.4">
			<file name="items.xml" url="https://raw.githubusercontent.com/teamstupeberron/aurora/main/teamstupeberron/items.xml" />
		</update>
	</info>
    <element name="Cone Of Silence" type="Magic Item" source="Team StupEberron" id="ID_TSE_MAGIC_ITEM_CONE_OF_SILENCE">
        <description>
            <p>When you push the button on this item once a day, it creates a sphere of silence.</p>
        </description>
        <setters>
            <set name="category">Wondrous Items</set>
            <set name="cost" currency="gp">0</set>
            <set name="weight" lb="0">0 lb.</set>
            <set name="type">Wondrous Item</set>
            <set name="rarity">Rare</set>
            <set name="slot">misc</set>
        </setters>
    </element> 
    <element name="Staff Of An Adder" type="Magic Item" source="Team StupEberron" id="ID_TSE_MAGIC_ITEM_STAFF_OF_AN_ADDER">
		<description>
			<p>You can use an action to speak this staff’s command word and throw the staff on the ground within 10 feet of you. The staff becomes a giant constrictor snake under your control and acts on its own initiative count. By using a bonus action to speak the command word again, you return the staff to its normal form in a space formerly occupied by the snake.</p>
			<p class="indent">On your turn, you can mentally command the snake if it is within 60 feet of you and you aren’t incapacitated. You decide what action the snake takes and where it moves during its next turn, or you can issue it a general command, such as to attack your enemies or guard a location.</p>
			<p class="indent">If the snake is reduced to 0 hit points, it dies and reverts to its staff form. The staff then shatters and is destroyed. If the snake reverts to staff form before losing all its hit points, it regains all of them.</p>
		</description>
		<setters>
			<set name="keywords">cleric, druid, warlock</set>
			<set name="category">Staffs</set>
			<set name="cost" currency="gp">0</set>
			<set name="weight" lb="4">4 lb.</set>
			<set name="slot">onehand</set>
			<set name="weapon">Quarterstaff</set>
			<set name="type">Staff</set>
			<set name="attunement" addition="by a cleric, druid, or warlock">true</set>
			<set name="rarity">Uncommon</set>
		</setters>
    </element>
	<element name="Sonic Kylie" type="Magic Item" source="Team StupEberron" id="ID_TSE_MAGIC_ITEM_SONIC_KYLIE">
		<supports>ID_INTERNAL_WEAPON_CATEGORY_SIMPLE_MELEE, ID_INTERNAL_DAMAGE_TYPE_BLUDGEONING, ID_INTERNAL_WEAPON_PROPERTY_THROWN, ID_INTERNAL_WEAPON_PROPERTY_FINESSE</supports>
		<description>
			<p>This magical boomerang hits harder on the way back. When you attack with it, roll to hit. If you succeed, The Sonic Kylie does 1d4 bludgeoning damage and automatically returns to your hand. However, if you miss your target, the Sonic Kylie spins off. At the start of your next turn, it returns and you may make a new attack roll with it against the same target. If the new attack roll hits, it instead does 1d4 bludgeoning damage plus 3d6 thunder damage. (effect continues if you miss again). Once the strong hit connects, you may then use your reaction to catch the boomerang. If you do not, it lands 30 feet away in a direction of DM’s choice.</p>
		</description>
		<setters>
			<set name="category">Wondrous Items</set>
			<set name="cost" currency="gp">0</set>
			<set name="weight" lb="2">2 lb.</set>
			<set name="type" addition="boomerang">Weapon</set>
			<set name="rarity">Rare</set>
			<set name="slot">onehand</set>
			<set name="range">60/120</set>
			<set name="attunement">true</set>
			<set name="damage" type="bludgeoning">1d4</set>
			<set name="proficiency">ID_PROFICIENCY_WEAPON_PROFICIENCY_SIMPLE_WEAPONS</set>
		</setters>
	</element>
	<element name="Estus" type="Magic Item" source="Team StupEberron" id="ID_TSE_MAGIC_ITEM_ESTUS">
		<description>
			<p>This bottle has two swigs of healing water, each of which heals 1d12 HP. It refills on a long rest.</p>
		</description>
		<setters>
			<set name="category">Wondrous Items</set>
			<set name="cost" currency="gp">0</set>
			<set name="weight" lb="1">1 lb.</set>
			<set name="type">Wondrous Item</set>
			<set name="rarity">Rare</set>
		</setters>
	</element>
	<element name="Ball Of Snow Rice" type="Magic Item" source="Team StupEberron" id="ID_TSE_MAGIC_ITEM_SNOWRICEBALL">
		<description>
			<p>This small ball of magical rice restores 4D4+4 HP upon consumption, and another 4D4+4 HP at the start of the next round.</p>
		</description>
		<setters>
			<set name="category">Wondrous Items</set>
			<set name="cost" currency="gp">0</set>
			<set name="weight" lb="0">0 lb.</set>
			<set name="type">Wondrous Item</set>
			<set name="rarity">Rare</set>
		</setters>
	</element>
	<element name="Black and Yellow" type="Magic Item" source="Team StupEberron" id="ID_TSE_MAGIC_ITEM_BLACKNYELLOW">
		<description>
			<p>This black and yellow pendant is made from dragonshard and can cast one of the following spells once a day:</p>
			<p class="indent"><strong><em>Dust of Dissapearance:</em></strong>  10 ft invisibility for 2d4 minutes</p>
			<p class="indent"><strong><em>Flash of Truth:</em></strong>  (Wis Save DC 14), 1 question</p>
			<p class="indent"><strong><em>Hold Portal</em></strong></p>
		</description>
		<setters>
			<set name="category">Wondrous Items</set>
			<set name="cost" currency="gp">0</set>
			<set name="weight" lb="0">0 lb.</set>
			<set name="type">Wondrous Item</set>
			<set name="slot">neck</set>
			<set name="rarity">Rare</set>
		</setters>
	</element>
</elements>